LICENSE.txt
MANIFEST.in
README.rst
setup.py
ox_ui/__init__.py
ox_ui.egg-info/PKG-INFO
ox_ui.egg-info/SOURCES.txt
ox_ui.egg-info/dependency_links.txt
ox_ui.egg-info/entry_points.txt
ox_ui.egg-info/requires.txt
ox_ui.egg-info/top_level.txt
ox_ui/assets/__init__.py
ox_ui/assets/css/__init__.py
ox_ui/assets/css/w3.css
ox_ui/core/__init__.py
ox_ui/core/c2f.py
ox_ui/core/c2g.py
ox_ui/core/decorators.py
ox_ui/core/sample_wtf.html
ox_ui/test_tools/__init__.py
ox_ui/test_tools/server_tools.py