Metadata-Version: 1.1
Name: ox-ui
Version: 0.3.9
Summary: Simple user interface tools for python
Home-page: http://github.com/emin63/ox_ui
Author: Emin Martinian
Author-email: emin.martinian@gmail.com
License: custom
Keywords: flask click ui
Platform: UNKNOWN
Classifier: Development Status :: 3 - Alpha
Classifier: Intended Audience :: Developers
Classifier: Programming Language :: Python :: 3
